codeblocks/__init__.py
codeblocks-0.4.1.dist-info/METADATA
codeblocks-0.4.1.dist-info/WHEEL
codeblocks-0.4.1.dist-info/entry_points.txt
codeblocks-0.4.1.dist-info/licenses/LICENSE
codeblocks-0.4.1.dist-info/RECORD
