Metadata-Version: 2.3
Name: codeblocks
Version: 0.4.1
Summary: Extract and process code blocks from Markdown files.
Author-email: Alexey Shamrin <alexey@gmail.com>
Requires-Python: >=3.9
Requires-Dist: click~=8.1
